awesome_math/__init__.py
awesome_math/core.py
tests/test_core.py
awesome_math-0.1.0.dist-info/METADATA
awesome_math-0.1.0.dist-info/WHEEL
awesome_math-0.1.0.dist-info/top_level.txt
awesome_math-0.1.0.dist-info/RECORD
