Metadata-Version: 2.4
Name: awesome-math
Version: 0.1.0
Summary: A tiny example math library
Author-email: Your Name <you@example.com>
License: MIT
Requires-Python: >=3.9
